database_helper/__init__.py
database_helper/database/__init__.py
database_helper/database/async_db.py
database_helper/database/base.py
database_helper/database/constants_conn.py
database_helper/database/model_enum.py
database_helper/database/model_mappings.py
database_helper/database/models.py
database_helper/database/sync_db.py
database_helper/database/sync_db2.py
database_helper/database/utilities.py
tests/__init__.py
tests/test_async_database.py
tests/test_sync_database.py
locobuzz_python_orm-1.1.5.dist-info/METADATA
locobuzz_python_orm-1.1.5.dist-info/WHEEL
locobuzz_python_orm-1.1.5.dist-info/top_level.txt
locobuzz_python_orm-1.1.5.dist-info/RECORD
