Metadata-Version: 2.1
Name: locobuzz-python-orm
Version: 1.1.5
Summary: Python database orm functions for Locobuzz,  common code that is required in all projects
Home-page: https://github.com/LocoBuzz-Solutions-Pvt-Ltd/locobuzz_database_orm
Author: Atharva Udavant
Author-email: atharva.udavant@locobuzz.com
Keywords: locobuzz,python,database
Classifier: Development Status :: 4 - Beta
Classifier: Programming Language :: Python :: 3
Classifier: Programming Language :: Python :: 3.8
Classifier: Programming Language :: Python :: 3.9
Classifier: Programming Language :: Python :: 3.10
Classifier: License :: OSI Approved :: MIT License
Classifier: Operating System :: OS Independent
Requires-Python: >=3.8, <=3.12
Requires-Dist: Cython
Requires-Dist: sqlalchemy
Requires-Dist: pyodbc
Requires-Dist: aioodbc
Requires-Dist: aiomysql
Requires-Dist: asyncpg
Provides-Extra: dataframe
Requires-Dist: pandas ; extra == 'dataframe'
